devicecloud/__init__.py
devicecloud/apibase.py
devicecloud/conditions.py
devicecloud/devicecore.py
devicecloud/file_system_service.py
devicecloud/filedata.py
devicecloud/monitor.py
devicecloud/monitor_tcp.py
devicecloud/sci.py
devicecloud/streams.py
devicecloud/util.py
devicecloud/version.py
devicecloud/ws.py
devicecloud/data/__init__.py
devicecloud/examples/__init__.py
devicecloud/examples/cookbook_streams.py
devicecloud/examples/devicecore_playground.py
devicecloud/examples/example_helpers.py
devicecloud/examples/file_system_service_playground.py
devicecloud/examples/filedata_playground.py
devicecloud/examples/monitor_playground.py
devicecloud/examples/streams_playground.py
devicecloud/examples/test.py
devicecloud/test/__init__.py
devicecloud/test/integration/__init__.py
devicecloud/test/integration/inttest_monitor_tcp.py
devicecloud/test/integration/inttest_streams.py
devicecloud/test/integration/inttest_utilities.py
devicecloud/test/unit/__init__.py
devicecloud/test/unit/test_conditions.py
devicecloud/test/unit/test_core.py
devicecloud/test/unit/test_devicecore.py
devicecloud/test/unit/test_file_system_service.py
devicecloud/test/unit/test_filedata.py
devicecloud/test/unit/test_monitor.py
devicecloud/test/unit/test_monitor_tcp.py
devicecloud/test/unit/test_sci.py
devicecloud/test/unit/test_streams.py
devicecloud/test/unit/test_utilities.py
devicecloud/test/unit/test_version.py
devicecloud/test/unit/test_ws.py
devicecloud-0.5.10.dist-info/licenses/LICENSE
devicecloud-0.5.10.dist-info/METADATA
devicecloud-0.5.10.dist-info/WHEEL
devicecloud-0.5.10.dist-info/top_level.txt
devicecloud-0.5.10.dist-info/RECORD
