Metadata-Version: 2.4
Name: devicecloud
Version: 0.5.10
Summary: Python API to the Digi Device Cloud
Home-page: https://github.com/digidotcom/python-devicecloud
Author: Digi International Inc.
Author-email: brandon.moser@digi.com
Classifier: Development Status :: 4 - Beta
Classifier: Intended Audience :: Developers
Classifier: License :: OSI Approved :: Mozilla Public License 2.0 (MPL 2.0)
Classifier: Programming Language :: Python :: 2.7
Classifier: Programming Language :: Python :: 3
Classifier: Programming Language :: Python :: 3.4
Classifier: Programming Language :: Python :: 3.5
Classifier: Programming Language :: Python :: 3.6
Classifier: Programming Language :: Python :: 3.7
Classifier: Topic :: Software Development :: Libraries
Classifier: Operating System :: OS Independent
License-File: LICENSE
Requires-Dist: arrow>=1.2.2
Requires-Dist: backports.functools-lru-cache>=1.5
Requires-Dist: certifi>=2021.10.8
Requires-Dist: chardet>=4.0.0
Requires-Dist: idna>=3.3
Requires-Dist: python-dateutil>=2.8.2
Requires-Dist: requests>=2.27.1
Requires-Dist: six>=1.16.0
Requires-Dist: urllib3>=1.22
Dynamic: author
Dynamic: author-email
Dynamic: classifier
Dynamic: description
Dynamic: description-content-type
Dynamic: home-page
Dynamic: license-file
Dynamic: requires-dist
Dynamic: summary
